JiqiXuexiJiaochengShareditor/README.md
JiqiXuexiJiaochengShareditor/__init__.py
JiqiXuexiJiaochengShareditor/__main__.py
JiqiXuexiJiaochengShareditor/file.epub
JiqiXuexiJiaochengShareditor/index.html
JiqiXuexiJiaochengShareditor/css/__init__.py
JiqiXuexiJiaochengShareditor/css/annotations.css
JiqiXuexiJiaochengShareditor/css/main.css
JiqiXuexiJiaochengShareditor/css/normalize.css
JiqiXuexiJiaochengShareditor/css/popup.css
JiqiXuexiJiaochengShareditor/font/__init__.py
JiqiXuexiJiaochengShareditor/font/fontello.eot
JiqiXuexiJiaochengShareditor/font/fontello.svg
JiqiXuexiJiaochengShareditor/font/fontello.ttf
JiqiXuexiJiaochengShareditor/font/fontello.woff
JiqiXuexiJiaochengShareditor/img/__init__.py
JiqiXuexiJiaochengShareditor/img/annotator-glyph-sprite.png
JiqiXuexiJiaochengShareditor/img/annotator-icon-sprite.png
JiqiXuexiJiaochengShareditor/img/apple-touch-icon.png
JiqiXuexiJiaochengShareditor/img/cancelfullscreen.png
JiqiXuexiJiaochengShareditor/img/close.png
JiqiXuexiJiaochengShareditor/img/fullscreen.png
JiqiXuexiJiaochengShareditor/img/loader.gif
JiqiXuexiJiaochengShareditor/img/menu-icon.png
JiqiXuexiJiaochengShareditor/img/save.png
JiqiXuexiJiaochengShareditor/img/saved.png
JiqiXuexiJiaochengShareditor/img/settings-s.png
JiqiXuexiJiaochengShareditor/img/settings.png
JiqiXuexiJiaochengShareditor/img/star.png
JiqiXuexiJiaochengShareditor/js/__init__.py
JiqiXuexiJiaochengShareditor/js/epub.js
JiqiXuexiJiaochengShareditor/js/epub.min.js
JiqiXuexiJiaochengShareditor/js/epub.min.map
JiqiXuexiJiaochengShareditor/js/hooks.min.js
JiqiXuexiJiaochengShareditor/js/hooks.min.map
JiqiXuexiJiaochengShareditor/js/reader.js
JiqiXuexiJiaochengShareditor/js/reader.js.map
JiqiXuexiJiaochengShareditor/js/reader.min.js
JiqiXuexiJiaochengShareditor/js/reader.min.map
JiqiXuexiJiaochengShareditor/js/hooks/__init__.py
JiqiXuexiJiaochengShareditor/js/hooks/extensions/__init__.py
JiqiXuexiJiaochengShareditor/js/hooks/extensions/highlight.js
jiqi_xuexi_jiaocheng_shareditor-2024.3.3.0.dist-info/METADATA
jiqi_xuexi_jiaocheng_shareditor-2024.3.3.0.dist-info/WHEEL
jiqi_xuexi_jiaocheng_shareditor-2024.3.3.0.dist-info/entry_points.txt
jiqi_xuexi_jiaocheng_shareditor-2024.3.3.0.dist-info/top_level.txt
jiqi_xuexi_jiaocheng_shareditor-2024.3.3.0.dist-info/RECORD
